aiida_qe_xspec/__init__.py
aiida_qe_xspec/__main__.py
aiida_qe_xspec/utils.py
aiida_qe_xspec/calculations/__init__.py
aiida_qe_xspec/calculations/xspectra.py
aiida_qe_xspec/calculations/functions/xspectra/__init__.py
aiida_qe_xspec/calculations/functions/xspectra/get_powder_spectrum.py
aiida_qe_xspec/calculations/functions/xspectra/get_spectra_by_element.py
aiida_qe_xspec/calculations/functions/xspectra/get_xps_spectra.py
aiida_qe_xspec/calculations/functions/xspectra/merge_spectra.py
aiida_qe_xspec/gui/__init__.py
aiida_qe_xspec/gui/xas/__init__.py
aiida_qe_xspec/gui/xas/model.py
aiida_qe_xspec/gui/xas/resources.py
aiida_qe_xspec/gui/xas/setting.py
aiida_qe_xspec/gui/xas/workchain.py
aiida_qe_xspec/gui/xas/result/__init__.py
aiida_qe_xspec/gui/xas/result/model.py
aiida_qe_xspec/gui/xas/result/result.py
aiida_qe_xspec/gui/xas/result/spectrum_button.py
aiida_qe_xspec/gui/xas/result/utils.py
aiida_qe_xspec/gui/xas/structure_examples/Li2CO3.cif
aiida_qe_xspec/gui/xas/structure_examples/__init__.py
aiida_qe_xspec/gui/xps/__init__.py
aiida_qe_xspec/gui/xps/model.py
aiida_qe_xspec/gui/xps/resources.py
aiida_qe_xspec/gui/xps/setting.py
aiida_qe_xspec/gui/xps/workchain.py
aiida_qe_xspec/gui/xps/guides/0_Basic tutorial.html
aiida_qe_xspec/gui/xps/result/__init__.py
aiida_qe_xspec/gui/xps/result/model.py
aiida_qe_xspec/gui/xps/result/result.py
aiida_qe_xspec/gui/xps/result/utils.py
aiida_qe_xspec/gui/xps/structure_examples/Al.cif
aiida_qe_xspec/gui/xps/structure_examples/ETFA.xyz
aiida_qe_xspec/gui/xps/structure_examples/Phenylacetylene.xyz
aiida_qe_xspec/gui/xps/structure_examples/__init__.py
aiida_qe_xspec/parsers/xspectra.py
aiida_qe_xspec/workflows/__init__.py
aiida_qe_xspec/workflows/xps.py
aiida_qe_xspec/workflows/functions/__init__.py
aiida_qe_xspec/workflows/functions/get_marked_structures.py
aiida_qe_xspec/workflows/functions/get_xspectra_structures.py
aiida_qe_xspec/workflows/protocols/core_hole_treatments.yaml
aiida_qe_xspec/workflows/protocols/xps.yaml
aiida_qe_xspec-0.1.6.dist-info/entry_points.txt
aiida_qe_xspec-0.1.6.dist-info/licenses/LICENSE
aiida_qe_xspec-0.1.6.dist-info/WHEEL
aiida_qe_xspec-0.1.6.dist-info/METADATA
aiida_qe_xspec-0.1.6.dist-info/RECORD
